graphite_beacon_cron/__init__.py
graphite_beacon_cron/_compat.py
graphite_beacon_cron/alerts.py
graphite_beacon_cron/app.py
graphite_beacon_cron/core.py
graphite_beacon_cron/graphite.py
graphite_beacon_cron/template.py
graphite_beacon_cron/utils.py
graphite_beacon_cron/handlers/__init__.py
graphite_beacon_cron/handlers/cli.py
graphite_beacon_cron/handlers/hipchat.py
graphite_beacon_cron/handlers/http.py
graphite_beacon_cron/handlers/log.py
graphite_beacon_cron/handlers/opsgenie.py
graphite_beacon_cron/handlers/pagerduty.py
graphite_beacon_cron/handlers/slack.py
graphite_beacon_cron/handlers/smtp.py
graphite_beacon_cron/handlers/telegram.py
graphite_beacon_cron/handlers/victorops.py
graphite_beacon_cron/templates/base.html
graphite_beacon_cron/templates/common/message.html
graphite_beacon_cron/templates/common/message.txt
graphite_beacon_cron/templates/common/short.txt
graphite_beacon_cron/templates/graphite/message.html
graphite_beacon_cron/templates/graphite/message.txt
graphite_beacon_cron/templates/graphite/short.txt
graphite_beacon_cron/templates/graphite/slack.txt
graphite_beacon_cron/templates/url/message.html
graphite_beacon_cron/templates/url/message.txt
graphite_beacon_cron/templates/url/short.txt
graphite_beacon_cron-0.25.4.2.dist-info/DESCRIPTION.rst
graphite_beacon_cron-0.25.4.2.dist-info/METADATA
graphite_beacon_cron-0.25.4.2.dist-info/RECORD
graphite_beacon_cron-0.25.4.2.dist-info/WHEEL
graphite_beacon_cron-0.25.4.2.dist-info/entry_points.txt
graphite_beacon_cron-0.25.4.2.dist-info/metadata.json
graphite_beacon_cron-0.25.4.2.dist-info/top_level.txt
