Metadata-Version: 2.0
Name: graphite-beacon-cron
Version: 0.25.4.2
Summary: Simple alerting system for Graphite metrics.
Requires-Dist: croniter (==0.3.10)
Requires-Dist: funcparserlib (==0.3.6)
Requires-Dist: tornado (==4.1.0)
